CHANGELOG.txt
LICENSE.txt
MANIFEST.in
README.txt
setup.py
forest305/__init__.py
forest305/functions.py
forest305/greet.py
forest305.egg-info/PKG-INFO
forest305.egg-info/SOURCES.txt
forest305.egg-info/dependency_links.txt
forest305.egg-info/top_level.txt